fig.py
plotops-1.0.dist-info/licenses/LICENSE
plotops-1.0.dist-info/METADATA
plotops-1.0.dist-info/WHEEL
plotops-1.0.dist-info/top_level.txt
plotops-1.0.dist-info/RECORD
