Metadata-Version: 2.4
Name: plotops
Version: 1.0
Summary: Package provides python plotting tools
Author-email: "O. W. Petersen" <oyvind.w.petersen@ntnu.no>
Project-URL: repository, https://github.com/Oyvindwpetersen/plotops
Requires-Python: >=3
License-File: LICENSE
Requires-Dist: numpy
Dynamic: license-file
